wfc/__init__.py
wfc/rule.py
wfc/state.py
wfc/wave.py
pywfc-0.0.0.dist-info/METADATA
pywfc-0.0.0.dist-info/WHEEL
pywfc-0.0.0.dist-info/top_level.txt
pywfc-0.0.0.dist-info/RECORD
