Metadata-Version: 2.1
Name: pywfc
Version: 0.0.0
Summary: Python3 Wave Function Collapse Algorithm implementation
Home-page: https://github.com/FoxNerdSaysMoo/PyWFC
Author: TeamNightSky
Author-email: teamnightsky.gh@gmail.com
License: UNKNOWN
Platform: UNKNOWN
Classifier: Operating System :: OS Independent
Requires-Python: >=3.6
